rwrap/__init__.py
rwrap/converter.py
rwrap/wrapper.py
rwrap-0.2.0.dist-info/LICENSE
rwrap-0.2.0.dist-info/WHEEL
rwrap-0.2.0.dist-info/METADATA
rwrap-0.2.0.dist-info/RECORD
