Metadata-Version: 2.1
Name: rwrap
Version: 0.2.0
Summary: A thin wrapper around rpy2 with strong opinions on how data types should be converted.
Home-page: https://github.com/kpj/rwrap
License: MIT
Author: kpj
Author-email: kim.philipp.jablonski@gmail.com
Requires-Python: >=3.8.0,<4.0.0
Classifier: License :: OSI Approved :: MIT License
Classifier: Programming Language :: Python :: 3
Classifier: Programming Language :: Python :: 3.8
Classifier: Programming Language :: Python :: 3.9
Requires-Dist: Shapely (>=1.8.0,<2.0.0)
Requires-Dist: geopandas (>=0.10.2,<0.11.0)
Requires-Dist: loguru (>=0.5.3,<0.6.0)
Requires-Dist: numpy (>=1.22.1,<2.0.0)
Requires-Dist: pandas (>=1.4.0,<2.0.0)
Requires-Dist: rpy2 (>=3.4.5,<4.0.0)
Project-URL: Repository, https://github.com/kpj/rwrap
